{
  "project_info": {
    "project_number": "1054906404385",
    "firebase_url": "https://mobiiot-60f89-default-rtdb.asia-southeast1.firebasedatabase.app",
    "project_id": "mobiiot-60f89",
    "storage_bucket": "mobiiot-60f89.firebasestorage.app"
  },
  "client": [
    {
      "client_info": {
        "mobilesdk_app_id": "1:1054906404385:android:cb6ef9d1a9b2c4cf251d60",
        "android_client_info": {
          "package_name": "com.bangraja.smartwatertank"
        }
      },
      "oauth_client": [
        {
          "client_id": "1054906404385-p4gi8asp26jthutd410t953jmddr2fng.apps.googleusercontent.com",
          "client_type": 3
        }
      ],
      "api_key": [
        {
          "current_key": "AIzaSyCp4RxPe61-wpiuxHivNnlWaNOr2hML-XQ"
        }
      ],
      "services": {
        "appinvite_service": {
          "other_platform_oauth_client": [
            {
              "client_id": "1054906404385-p4gi8asp26jthutd410t953jmddr2fng.apps.googleusercontent.com",
              "client_type": 3
            }
          ]
        }
      }
    }
  ],
  "configuration_version": "1"
}